<?xml version="1.0" encoding="UTF-8"?><record_update table="sp_instance">
    <sp_instance action="DELETE">
        <active>true</active>
        <class_name/>
        <color>default</color>
        <css/>
        <glyph/>
        <id/>
        <order>1</order>
        <roles/>
        <short_description/>
        <size>md</size>
        <sp_column display_value="1">36aad79fc316761002cdb34ed4013189</sp_column>
        <sp_widget display_value="IT Request Widget">768e3e4fc3def21002cdb34ed401315b</sp_widget>
        <sys_class_name>sp_instance</sys_class_name>
        <sys_created_by>admin</sys_created_by>
        <sys_created_on>2026-01-13 07:38:06</sys_created_on>
        <sys_id>63aa979fc316761002cdb34ed4013112</sys_id>
        <sys_mod_count>0</sys_mod_count>
        <sys_name/>
        <sys_package display_value="Asset Request and Tracking" source="x_1862743_asset_re">e02165eac3d2721002cdb34ed4013167</sys_package>
        <sys_policy/>
        <sys_scope display_value="Asset Request and Tracking">e02165eac3d2721002cdb34ed4013167</sys_scope>
        <sys_update_name>sp_instance_63aa979fc316761002cdb34ed4013112</sys_update_name>
        <sys_updated_by>admin</sys_updated_by>
        <sys_updated_on>2026-01-13 07:38:06</sys_updated_on>
        <title/>
        <url/>
        <widget_parameters/>
    </sp_instance>
    <sys_translated_text action="DELETE" query="documentkey=63aa979fc316761002cdb34ed4013112"/>
    <sys_update_version action="INSERT_OR_UPDATE">
        <action>DELETE</action>
        <application display_value="Asset Request and Tracking">e02165eac3d2721002cdb34ed4013167</application>
        <file_path/>
        <instance_id>11226e861bfd711c699443f4bd4bcb5e</instance_id>
        <instance_name>dev183548</instance_name>
        <name>sp_instance_63aa979fc316761002cdb34ed4013112</name>
        <payload><![CDATA[<?xml version="1.0" encoding="UTF-8"?><record_update table="sp_instance"><sp_instance action="INSERT_OR_UPDATE"><active>true</active><class_name/><color>default</color><css/><glyph/><id/><order>1</order><roles/><short_description/><size>md</size><sp_column display_value="1">36aad79fc316761002cdb34ed4013189</sp_column><sp_widget display_value="IT Request Widget">768e3e4fc3def21002cdb34ed401315b</sp_widget><sys_class_name>sp_instance</sys_class_name><sys_created_by>admin</sys_created_by><sys_created_on>2026-01-13 07:38:06</sys_created_on><sys_id>63aa979fc316761002cdb34ed4013112</sys_id><sys_mod_count>0</sys_mod_count><sys_name/><sys_package display_value="Asset Request and Tracking" source="x_1862743_asset_re">e02165eac3d2721002cdb34ed4013167</sys_package><sys_policy/><sys_scope display_value="Asset Request and Tracking">e02165eac3d2721002cdb34ed4013167</sys_scope><sys_update_name>sp_instance_63aa979fc316761002cdb34ed4013112</sys_update_name><sys_updated_by>admin</sys_updated_by><sys_updated_on>2026-01-13 07:38:06</sys_updated_on><title/><url/><widget_parameters/></sp_instance><sys_translated_text action="delete_multiple" query="documentkey=63aa979fc316761002cdb34ed4013112"/></record_update>]]></payload>
        <payload_hash>534477246</payload_hash>
        <record_name/>
        <reverted_from/>
        <source>d21b2de6c316721002cdb34ed40131a5</source>
        <source_table>sys_update_set</source_table>
        <state>previous</state>
        <sys_created_by>admin</sys_created_by>
        <sys_created_on>2026-01-13 07:38:06</sys_created_on>
        <sys_id>27aa979fc316761002cdb34ed4013115</sys_id>
        <sys_mod_count>0</sys_mod_count>
        <sys_recorded_at>19bb64a602c0000001</sys_recorded_at>
        <sys_updated_by>admin</sys_updated_by>
        <sys_updated_on>2026-01-13 07:38:06</sys_updated_on>
        <type>Instance</type>
        <update_guid>2baa979fac167610e09d49b9d8f4d814</update_guid>
        <update_guid_history>2baa979fac167610e09d49b9d8f4d814:534477246</update_guid_history>
    </sys_update_version>
    <sys_metadata_delete action="INSERT_OR_UPDATE">
        <sys_audit_delete display_value="">83ba9b9fc316761002cdb34ed4013133</sys_audit_delete>
        <sys_class_name>sys_metadata_delete</sys_class_name>
        <sys_created_by>admin</sys_created_by>
        <sys_created_on>2026-01-13 07:38:20</sys_created_on>
        <sys_db_object display_value="" name="sp_instance">sp_instance</sys_db_object>
        <sys_id>0c26172bacae46f083e7a57e519c0211</sys_id>
        <sys_metadata>63aa979fc316761002cdb34ed4013112</sys_metadata>
        <sys_mod_count>0</sys_mod_count>
        <sys_name/>
        <sys_package display_value="Asset Request and Tracking" source="x_1862743_asset_re">e02165eac3d2721002cdb34ed4013167</sys_package>
        <sys_parent/>
        <sys_policy/>
        <sys_scope display_value="Asset Request and Tracking">e02165eac3d2721002cdb34ed4013167</sys_scope>
        <sys_scope_delete display_value="">0a9f05ad17ca421d8084cc2c45e19869</sys_scope_delete>
        <sys_update_name>sp_instance_63aa979fc316761002cdb34ed4013112</sys_update_name>
        <sys_update_version display_value="sp_instance_63aa979fc316761002cdb34ed4013112">27aa979fc316761002cdb34ed4013115</sys_update_version>
        <sys_updated_by>admin</sys_updated_by>
        <sys_updated_on>2026-01-13 07:38:20</sys_updated_on>
    </sys_metadata_delete>
</record_update>
